susc/__init__.py
susc/__main__.py
susc/exceptions.py
susc/explain.py
susc/lang_server.py
susc/linker.py
susc/log.py
susc/sus.lark
susc/things.py
susc/output/html/__init__.py
susc/output/html/topbar_default.png
susc/output/html/static/Montserrat-VF.woff2
susc/output/html/static/style.css
susc/output/print_ast/__init__.py
susc/output/ts/__init__.py
susc/stdlib/impostor.sus
susc-1.5.5.dist-info/LICENSE.md
susc-1.5.5.dist-info/METADATA
susc-1.5.5.dist-info/WHEEL
susc-1.5.5.dist-info/entry_points.txt
susc-1.5.5.dist-info/top_level.txt
susc-1.5.5.dist-info/RECORD
