Metadata-Version: 2.1
Name: susc
Version: 1.5.5
Summary: SpeedAPI schema compiler
Home-page: https://github.com/speedapi/susc
Author: portasynthinca3
Author-email: hi@portasynthinca3.me
License: BSD 3-Clause
Keywords: api,protocol,language
Platform: UNKNOWN
License-File: LICENSE.md
Requires-Dist: lark
Requires-Dist: colorama
Requires-Dist: markdown
Requires-Dist: nanoid
Requires-Dist: wheel
Requires-Dist: pygls
